adder.t.v
// Adder testbench
`timescale 1 ns / 1 ps
`include "adder.v"

module testFullAdder();
    reg a, b, carryin;
    wire sum, carryout;

    // behavioralFullAdder adder (sum, carryout, a, b, carryin);
    structuralFullAdder adder (sum, carryout, a, b, carryin);

    initial begin
    $dumpfile("adder.vcd");
    $dumpvars;
    
    $display("A  B  CarryIn| Sum CarryOut | ExpectedSum ExpectedCarryout");
    a=0; b=0; carryin=0; #1000
	$display("%b  %b   %b     | %b         %b  | 0              0", a, b, carryin, sum, carryout);
    a=1; b=0; carryin=0; #1000
	$display("%b  %b   %b     | %b         %b  | 1              0", a, b, carryin, sum, carryout);
    a=0; b=1; carryin=0; #1000
	$display("%b  %b   %b     | %b         %b  | 1              0", a, b, carryin, sum, carryout);
    a=1; b=1; carryin=0; #1000
	$display("%b  %b   %b     | %b         %b  | 0              1", a, b, carryin, sum, carryout);
    a=0; b=0; carryin=1; #1000
	$display("%b  %b   %b     | %b         %b  | 1              0", a, b, carryin, sum, carryout);
    a=1; b=0; carryin=1; #1000
	$display("%b  %b   %b     | %b         %b  | 0              1", a, b, carryin, sum, carryout);
    a=0; b=1; carryin=1; #1000
	$display("%b  %b   %b     | %b         %b  | 0              1", a, b, carryin, sum, carryout);
    a=1; b=1; carryin=1; #1000
	$display("%b  %b   %b     | %b         %b  | 1              1", a, b, carryin, sum, carryout);
    end
endmodule

adder.v
// Adder circuit

`define AND and #50
`define OR or #50
`define NOT not #50
`define XOR xor #50

module behavioralFullAdder
(
    output sum, 
    output carryout,
    input a, 
    input b, 
    input carryin
);
    // Uses concatenation operator and built-in '+'
    assign {carryout, sum}=a+b+carryin;
endmodule

module structuralFullAdder
(
    output sum, 
    output carryout,
    input a, 
    input b, 
    input carryin
);
    wire AandB, AandC, BandC;

    `XOR xorGate(sum, a, b, carryin);

    `AND andGate0(AandB, a, b);
    `AND andGate1(AandC, a, carryin);
    `AND andGate2(BandC, b, carryin);

    `OR orGate(carryout, AandB, AandC, BandC);

endmodule

adder.vcd
$date
	Fri Sep 23 04:30:13 2016
$end
$version
	Icarus Verilog
$end
$timescale
	1ps
$end
$scope module behavioralFullAdder $end
$var wire 1 ! a $end
$var wire 1 " b $end
$var wire 1 # carryin $end
$var wire 1 $ carryout $end
$var wire 1 % sum $end
$upscope $end
$scope module testFullAdder $end
$var wire 1 & carryout $end
$var wire 1 ' sum $end
$var reg 1 ( a $end
$var reg 1 ) b $end
$var reg 1 * carryin $end
$scope module adder $end
$var wire 1 + AandB $end
$var wire 1 , AandC $end
$var wire 1 - BandC $end
$var wire 1 . a $end
$var wire 1 / b $end
$var wire 1 0 carryin $end
$var wire 1 & carryout $end
$var wire 1 ' sum $end
$upscope $end
$upscope $end
$enddefinitions $end
#0
$dumpvars
00
0/
0.
z-
z,
z+
0*
0)
0(
z'
x&
x%
x$
z#
z"
z!
$end
#50000
0-
0,
0+
0'
#100000
0&
#1000000
1(
1.
#1050000
1'
#2000000
1)
1/
0(
0.
#3000000
1(
1.
#3050000
0'
1+
#3100000
1&
#4000000
1*
10
0)
0/
0(
0.
#4050000
1'
0+
#4100000
0&
#5000000
1(
1.
#5050000
0'
1,
#5100000
1&
#6000000
1)
1/
0(
0.
#6050000
1-
0,
#7000000
1(
1.
#7050000
1'
1+
1,
