adder.t.v
// Adder testbench
`timescale 1 ns / 1 ps
`include "adder.v"

module testFullAdder();
    reg a, b, carryin;
    wire sum, carryout;

    structuralFullAdder adder (sum, carryout, a, b, carryin);

    initial begin
        $display("A B C | Cout Sum | Expected Output");
	a=0; b=0; carryin=0; #1000
	$display("%b %b %b | %b%b | 00", a, b, carryin, carryout, sum);
	a=0; b=0; carryin=1; #1000
	$display("%b %b %b | %b%b | 01", a, b, carryin, carryout, sum);
	a=0; b=1; carryin=0; #1000
	$display("%b %b %b | %b%b | 01", a, b, carryin, carryout, sum);
	a=0; b=1; carryin=1; #1000
	$display("%b %b %b | %b%b | 10", a, b, carryin, carryout, sum);
	a=1; b=0; carryin=0; #1000
	$display("%b %b %b | %b%b | 01", a, b, carryin, carryout, sum);
	a=1; b=0; carryin=1; #1000
	$display("%b %b %b | %b%b | 10", a, b, carryin, carryout, sum);
	a=1; b=1; carryin=0; #1000
	$display("%b %b %b | %b%b | 10", a, b, carryin, carryout, sum);
	a=1; b=1; carryin=1; #1000
	$display("%b %b %b | %b%b | 11", a, b, carryin, carryout, sum);
    end
endmodule

adder.v
// Adder circuit
`define AND and #50
`define OR or #50
`define NOT not #50
`define XOR xor #50

module behavioralFullAdder
(
    output sum, 
    output carryout,
    input a, 
    input b, 
    input carryin
);
    // Uses concatenation operator and built-in '+'
    assign {carryout, sum}=a+b+carryin;
endmodule

module structuralFullAdder
(
    output sum, 
    output carryout,
    input a, 
    input b, 
    input carryin
);
    // Your adder code here
    wire AxorB;
    wire AandB;
    wire AxorBandCin;

    `XOR xorgate1(AxorB, a, b);
    `XOR xorgate2(sum, AxorB, carryin);

    `AND andgate1(AandB, a, b);
    `AND andgate2(AxorBandCin, AxorB, carryin);
    `OR orgate(carryout, AandB, AxorBandCin);


endmodule

adder.vcd
$date
	Fri Sep 23 00:16:16 2016
$end
$version
	Icarus Verilog
$end
$timescale
	1ps
$end
$scope module behavioralFullAdder $end
$var wire 1 ! a $end
$var wire 1 " b $end
$var wire 1 # carryin $end
$var wire 1 $ carryout $end
$var wire 1 % sum $end
$upscope $end
$scope module testFullAdder $end
$var wire 1 & carryout $end
$var wire 1 ' sum $end
$var reg 1 ( a $end
$var reg 1 ) b $end
$var reg 1 * carryin $end
$scope module adder $end
$var wire 1 + AandB $end
$var wire 1 , AxorB $end
$var wire 1 - AxorBandCin $end
$var wire 1 . a $end
$var wire 1 / b $end
$var wire 1 0 carryin $end
$var wire 1 & carryout $end
$var wire 1 ' sum $end
$upscope $end
$upscope $end
$enddefinitions $end
#0
$dumpvars
00
0/
0.
z-
z,
z+
0*
0)
0(
x'
x&
x%
x$
z#
z"
z!
$end
#50000
0-
0+
0,
#100000
0&
0'
#1000000
1*
10
#1050000
1'
#2000000
0*
00
1)
1/
#2050000
0'
1,
#2100000
1'
#3000000
1*
10
#3050000
0'
1-
#3100000
1&
#4000000
0*
00
0)
0/
1(
1.
#4050000
1'
0-
#4100000
0&
#5000000
1*
10
#5050000
0'
1-
#5100000
1&
#6000000
0*
00
1)
1/
#6050000
1'
0-
0,
1+
#6100000
0'
#7000000
1*
10
#7050000
1'
