adder.t.v
// Adder testbench
`timescale 1 ns / 1 ps
`include "adder.v"

module testFullAdder();
    reg a, b, carryin;
    wire sum, carryout;

    structuralFullAdder adder (sum, carryout, a, b, carryin);

    initial begin

    	// Set dump file
    	$dumpfile("adder_results.vcd");
		$dumpvars;

    	$display("A B Cin | S Cout | Expected Output");
    	a=1; b=1; carryin=1; #1000 
    	$display("%b  %b  %b |  %b  %b | 1 1", a, b, carryin, sum, carryout);
    	a=1; b=1; carryin=0; #1000 
    	$display("%b  %b  %b |  %b  %b | 0 1", a, b, carryin, sum, carryout);
    	a=1; b=0; carryin=1; #1000 
    	$display("%b  %b  %b |  %b  %b | 0 1", a, b, carryin, sum, carryout);
    	a=1; b=0; carryin=0; #1000 
    	$display("%b  %b  %b |  %b  %b | 1 0", a, b, carryin, sum, carryout);
    	a=0; b=1; carryin=1; #1000 
    	$display("%b  %b  %b |  %b  %b | 0 1", a, b, carryin, sum, carryout);
    	a=0; b=1; carryin=0; #1000 
    	$display("%b  %b  %b |  %b  %b | 1 0", a, b, carryin, sum, carryout);
    	a=0; b=0; carryin=1; #1000 
    	$display("%b  %b  %b |  %b  %b | 1 0", a, b, carryin, sum, carryout);
    	a=0; b=0; carryin=0; #1000 
    	$display("%b  %b  %b |  %b  %b | 0 0", a, b, carryin, sum, carryout);
    end
endmodule

adder.v
// Adder circuit

// Declare time delays
`define AND and #50
`define OR or #50
`define XOR xor #50

module behavioralFullAdder
(
    output sum, 
    output carryout,
    input a, 
    input b, 
    input carryin
);
    // Uses concatenation operator and built-in '+'
    assign {carryout, sum}=a+b+carryin;
endmodule

module structuralFullAdder
(
    output sum, 
    output carryout,
    input a, 
    input b, 
    input carryin
);
    
    wire AxorB;
    wire AandB;
    wire AorBandCin;

    // Sum
    `XOR xorgate1(AxorB, a, b);
    `XOR xorgate2(sum, AxorB, carryin);

    // Carryout
    `AND andgate1(AandB, a, b);
    `OR orgate1(AorB, a, b);
    `AND andgate2(AorBandCin, AorB, carryin);
    `OR orgate2(carryout, AandB, AorBandCin);

endmodule

adder_results.vcd
$date
	Sat Sep 24 13:57:35 2016
$end
$version
	Icarus Verilog
$end
$timescale
	1ps
$end
$scope module behavioralFullAdder $end
$var wire 1 ! a $end
$var wire 1 " b $end
$var wire 1 # carryin $end
$var wire 1 $ carryout $end
$var wire 1 % sum $end
$upscope $end
$scope module testFullAdder $end
$var wire 1 & carryout $end
$var wire 1 ' sum $end
$var reg 1 ( a $end
$var reg 1 ) b $end
$var reg 1 * carryin $end
$scope module adder $end
$var wire 1 + AandB $end
$var wire 1 , AorB $end
$var wire 1 - AorBandCin $end
$var wire 1 . AxorB $end
$var wire 1 / a $end
$var wire 1 0 b $end
$var wire 1 1 carryin $end
$var wire 1 & carryout $end
$var wire 1 ' sum $end
$upscope $end
$upscope $end
$enddefinitions $end
#0
$dumpvars
11
10
1/
z.
x-
z,
z+
1*
1)
1(
x'
x&
x%
x$
z#
z"
z!
$end
#50000
1,
1+
0.
#100000
1-
1&
1'
#1000000
0*
01
#1050000
0'
0-
#2000000
1*
11
0)
00
#2050000
1'
1-
1.
0+
#2100000
0'
#3000000
0*
01
#3050000
1'
0-
#3100000
0&
#4000000
1*
11
1)
10
0(
0/
#4050000
0'
1-
#4100000
1&
#5000000
0*
01
#5050000
1'
0-
#5100000
0&
#6000000
1*
11
0)
00
#6050000
0'
1-
0.
0,
#6100000
1&
1'
0-
#6150000
0&
#7000000
0*
01
#7050000
0'
