adder.t.v
// Adder testbench
`timescale 1 ns / 1 ps
`include "adder.v"

module testFullAdder();
    reg a, b, carryin;
    wire sum, carryout;

    //behavioralFullAdder adder (sum, carryout, a, b, carryin);
    structuralFullAdder adder (sum, carryout, a, b, carryin);

    initial begin
    // Dump trace to gtkwave
    $dumpfile("adder_trace.vcd");
    $dumpvars;

    // Test pattern stimulus
    $display("A B Cin | Cout S  | Expected Output");
    a=0;b=0;carryin=0; #500
    $display("%b %b  %b  |  %b   %b  |  0  0", a, b, carryin, carryout, sum);
    a=0;b=0;carryin=1; #500
    $display("%b %b  %b  |  %b   %b  |  0  1", a, b, carryin, carryout, sum);
    a=0;b=1;carryin=0; #500
    $display("%b %b  %b  |  %b   %b  |  0  1", a, b, carryin, carryout, sum);
    a=0;b=1;carryin=1; #500
    $display("%b %b  %b  |  %b   %b  |  1  0", a, b, carryin, carryout, sum);
    a=1;b=0;carryin=0; #500
    $display("%b %b  %b  |  %b   %b  |  0  1", a, b, carryin, carryout, sum);
    a=1;b=0;carryin=1; #500
    $display("%b %b  %b  |  %b   %b  |  1  0", a, b, carryin, carryout, sum);
    a=1;b=1;carryin=0; #500
    $display("%b %b  %b  |  %b   %b  |  1  0", a, b, carryin, carryout, sum);
    a=1;b=1;carryin=1; #500
    $display("%b %b  %b  |  %b   %b  |  1  1", a, b, carryin, carryout, sum);
    end
endmodule

adder.v
// Adder circuit

module behavioralFullAdder
(
    output sum, 
    output carryout,
    input a, 
    input b, 
    input carryin
);
    // Uses concatenation operator and built-in '+'
    assign {carryout, sum}=a+b+carryin;
endmodule

// Set gate delays
`define AND and #50
`define OR or #50
`define NOT not #50
`define XOR xor #50

module structuralFullAdder
(
    output sum, 
    output carryout,
    input a, 
    input b, 
    input carryin
);
    // Helper gates
    wire n_b, n_carryin;
    `NOT notGate1(n_b, b);
    `NOT notGate2(n_carryin, carryin);

    wire AxorB, AxornB;
    `XOR xorGate1(AxorB, a, b);
    `XOR xorGate2(AxornB, a, n_b);

    // Calculates the sum
    wire sum1, sum2;
    `AND andGate1(sum1, n_carryin, AxorB);
    `AND andGate2(sum2, carryin, AxornB);
    `OR orGate1(sum, sum1, sum2);

    // Calculates the carryout
    wire carryout1, carryout2;
    `AND andGate3(carryout1, carryin, AxorB);
    `AND andGate4(carryout2, a, b);
    `OR orGate2(carryout, carryout1, carryout2);
endmodule

adder_trace.vcd
$date
	Fri Sep 23 00:22:49 2016
$end
$version
	Icarus Verilog
$end
$timescale
	1ps
$end
$scope module behavioralFullAdder $end
$var wire 1 ! a $end
$var wire 1 " b $end
$var wire 1 # carryin $end
$var wire 1 $ carryout $end
$var wire 1 % sum $end
$upscope $end
$scope module testFullAdder $end
$var wire 1 & carryout $end
$var wire 1 ' sum $end
$var reg 1 ( a $end
$var reg 1 ) b $end
$var reg 1 * carryin $end
$scope module adder $end
$var wire 1 + AxorB $end
$var wire 1 , AxornB $end
$var wire 1 - a $end
$var wire 1 . b $end
$var wire 1 / carryin $end
$var wire 1 & carryout $end
$var wire 1 0 carryout1 $end
$var wire 1 1 carryout2 $end
$var wire 1 2 n_b $end
$var wire 1 3 n_carryin $end
$var wire 1 ' sum $end
$var wire 1 4 sum1 $end
$var wire 1 5 sum2 $end
$upscope $end
$upscope $end
$enddefinitions $end
#0
$dumpvars
z5
x4
z3
z2
z1
z0
0/
0.
0-
x,
z+
0*
0)
0(
x'
x&
x%
x$
z#
z"
z!
$end
#50000
01
00
05
0+
12
13
#100000
0&
1,
04
#150000
0'
#500000
1*
1/
#550000
03
15
#600000
1'
#1000000
0*
0/
1)
1.
#1050000
13
05
02
1+
#1100000
0'
0,
14
#1150000
1'
#1500000
1*
1/
#1550000
03
10
#1600000
04
1&
#1650000
0'
#2000000
0*
0/
0)
0.
1(
1-
#2050000
13
00
12
1,
#2100000
14
0&
0,
#2150000
1'
#2500000
1*
1/
#2550000
03
10
#2600000
04
1&
#2650000
0'
#3000000
0*
0/
1)
1.
#3050000
13
00
02
0+
11
#3100000
1,
#3500000
1*
1/
#3550000
03
15
#3600000
1'
