adder.t.v
// Adder testbench
`timescale 1 ns / 1 ps
`include "adder.v"

module testFullAdder();
    reg a, b, carryin;
    wire sum, carryout;

    // behavioralFullAdder adder (sum, carryout, a, b, carryin);
    structuralFullAdder adder (sum, carryout, a, b, carryin);

    initial begin
    $dumpfile("adder.vcd");
    $dumpvars();
    $display("A  B  CI | Sum CO | Sum CO (Expected Output)");
    a=0;b=0;carryin=0; #500 
    $display("%b  %b  %b  |   %b  %b | 0   0", a, b, carryin, sum, carryout);
    a=1;b=0;carryin=0; #500
    $display("%b  %b  %b  |   %b  %b | 1   0", a, b, carryin, sum, carryout);
    a=0;b=1;carryin=0; #500 
    $display("%b  %b  %b  |   %b  %b | 1   0", a, b, carryin, sum, carryout);
    a=1;b=1;carryin=0; #500 
    $display("%b  %b  %b  |   %b  %b | 0   1", a, b, carryin, sum, carryout);
    a=0;b=0;carryin=1; #500 
    $display("%b  %b  %b  |   %b  %b | 1   0", a, b, carryin, sum, carryout);
    a=1;b=0;carryin=1; #500 
    $display("%b  %b  %b  |   %b  %b | 0   1", a, b, carryin, sum, carryout);
    a=0;b=1;carryin=1; #500 
    $display("%b  %b  %b  |   %b  %b | 0   1", a, b, carryin, sum, carryout);
    a=1;b=1;carryin=1; #500 
    $display("%b  %b  %b  |   %b  %b | 1   1", a, b, carryin, sum, carryout);
    $dumpflush;
    end
endmodule

adder.v
// Adder circuit

// define gates with delays
`define AND and #50
`define OR or #50
`define XOR xor #50

module behavioralFullAdder
(
    output sum, 
    output carryout,
    input a, 
    input b, 
    input carryin
);
    // Uses concatenation operator and built-in '+'
    assign {carryout, sum}=a+b+carryin;
endmodule

module structuralFullAdder
(
    output sum, 
    output carryout,
    input a, 
    input b, 
    input carryin
);
    wire a, b, carryin;
    wire na, nb, ncarryin;
    wire axorb, aandb, carryinandaxorb;

    `XOR xorgate0(axorb, a, b);
    `XOR xorgate1(sum, axorb, carryin);

    `AND andgate0(aandb, a, b);
    `AND andgate1(carryinandaxorb, carryin, axorb);
    `OR orgate(carryout, aandb, carryinandaxorb);

endmodule

adder.vcd
$date
	Thu Sep 22 00:51:33 2016
$end
$version
	Icarus Verilog
$end
$timescale
	1ps
$end
$scope module behavioralFullAdder $end
$var wire 1 ! a $end
$var wire 1 " b $end
$var wire 1 # carryin $end
$var wire 1 $ sum $end
$var wire 1 % carryout $end
$upscope $end
$scope module testFullAdder $end
$var wire 1 & sum $end
$var wire 1 ' carryout $end
$var reg 1 ( a $end
$var reg 1 ) b $end
$var reg 1 * carryin $end
$scope module adder $end
$var wire 1 ( a $end
$var wire 1 + aandb $end
$var wire 1 , axorb $end
$var wire 1 ) b $end
$var wire 1 * carryin $end
$var wire 1 - carryinandaxorb $end
$var wire 1 ' carryout $end
$var wire 1 & sum $end
$upscope $end
$upscope $end
$enddefinitions $end
#0
$dumpvars
x-
x,
x+
0*
0)
0(
x'
x&
x%
x$
z#
z"
z!
$end
#50000
0-
0+
0,
#100000
0'
0&
#500000
1(
#550000
1,
#600000
1&
#1000000
1)
0(
#1500000
1(
#1550000
0,
1+
#1600000
0&
1'
#2000000
1*
0)
0(
#2050000
1&
0+
#2100000
0'
#2500000
1(
#2550000
1,
#2600000
0&
1-
#2650000
1'
#3000000
1)
0(
#3500000
1(
#3550000
0,
1+
#3600000
1&
0-
