decoder.t.v
// Decoder testbench
`timescale 1 ns / 1 ps
`include "decoder.v"

module testDecoder (); 
    reg addr0, addr1;
    reg enable;
    wire out0,out1,out2,out3;

    //behavioralDecoder decoder (out0,out1,out2,out3,addr0,addr1,enable);
    structuralDecoder decoder (out0,out1,out2,out3,addr0,addr1,enable); // Swap after testing

    initial begin

    // Dump trace to a file. Open with gtkwave.
    $dumpfile("decoder.vcd");
    $dumpvars;

    $display("En A0 A1| O0 O1 O2 O3 | Expected Output");
    enable=0;addr0=0;addr1=0; #1000 
    $display("%b  %b  %b |  %b  %b  %b  %b | All false", enable, addr0, addr1, out0, out1, out2, out3);
    enable=0;addr0=1;addr1=0; #1000
    $display("%b  %b  %b |  %b  %b  %b  %b | All false", enable, addr0, addr1, out0, out1, out2, out3);
    enable=0;addr0=0;addr1=1; #1000 
    $display("%b  %b  %b |  %b  %b  %b  %b | All false", enable, addr0, addr1, out0, out1, out2, out3);
    enable=0;addr0=1;addr1=1; #1000 
    $display("%b  %b  %b |  %b  %b  %b  %b | All false", enable, addr0, addr1, out0, out1, out2, out3);
    enable=1;addr0=0;addr1=0; #1000 
    $display("%b  %b  %b |  %b  %b  %b  %b | O0 Only", enable, addr0, addr1, out0, out1, out2, out3);
    enable=1;addr0=1;addr1=0; #1000 
    $display("%b  %b  %b |  %b  %b  %b  %b | O1 Only", enable, addr0, addr1, out0, out1, out2, out3);
    enable=1;addr0=0;addr1=1; #1000 
    $display("%b  %b  %b |  %b  %b  %b  %b | O2 Only", enable, addr0, addr1, out0, out1, out2, out3);
    enable=1;addr0=1;addr1=1; #1000 
    $display("%b  %b  %b |  %b  %b  %b  %b | O3 Only", enable, addr0, addr1, out0, out1, out2, out3);
    end

endmodule

decoder.v
// Decoder circuit

// Setting Delays
`define AND and #50 //delay of 50 units
`define NOT not #50

module behavioralDecoder
(
    output out0, out1, out2, out3,
    input address0, address1,
    input enable
);
    // Uses concatenation and shift operators
    assign {out3,out2,out1,out0}=enable<<{address1,address0};
endmodule


module structuralDecoder
(
    output out0, out1, out2, out3,
    input address0, address1,
    input enable
);
    wire n_address0, n_address1;	// Inverted initial signal
    `NOT address0inv(n_address0,address0); // Relevant function for n_address#
    `NOT address1inv(n_address1,address1);

    `AND andgate_out0(out0, n_address0, n_address1, enable);	// intermediate and gate
    `AND andgate_out1(out1, address0, n_address1, enable);
    `AND andgate_out2(out2, n_address0, address1, enable);
    `AND andgate_out3(out3, address0, address1, enable);

endmodule

decoder.vcd
$date
	Wed Sep 21 02:53:02 2016
$end
$version
	Icarus Verilog
$end
$timescale
	1ps
$end
$scope module behavioralDecoder $end
$var wire 1 ! address0 $end
$var wire 1 " address1 $end
$var wire 1 # enable $end
$var wire 1 $ out0 $end
$var wire 1 % out1 $end
$var wire 1 & out2 $end
$var wire 1 ' out3 $end
$upscope $end
$scope module testDecoder $end
$var wire 1 ( out0 $end
$var wire 1 ) out1 $end
$var wire 1 * out2 $end
$var wire 1 + out3 $end
$var reg 1 , addr0 $end
$var reg 1 - addr1 $end
$var reg 1 . enable $end
$scope module decoder $end
$var wire 1 / address0 $end
$var wire 1 0 address1 $end
$var wire 1 1 enable $end
$var wire 1 2 n_address0 $end
$var wire 1 3 n_address1 $end
$var wire 1 ( out0 $end
$var wire 1 ) out1 $end
$var wire 1 * out2 $end
$var wire 1 + out3 $end
$upscope $end
$upscope $end
$enddefinitions $end
#0
$dumpvars
z3
z2
01
00
0/
0.
0-
0,
z+
z*
z)
z(
x'
x&
x%
x$
z#
z"
z!
$end
#50000
0+
0*
0)
0(
12
13
#1000000
1,
1/
#1050000
02
#2000000
1-
10
0,
0/
#2050000
03
12
#3000000
1,
1/
#3050000
02
#4000000
0-
00
0,
0/
1.
11
#4050000
13
12
#4100000
1(
#5000000
1,
1/
#5050000
02
1)
#5100000
0(
#6000000
1-
10
0,
0/
#6050000
03
12
0)
#6100000
1*
#7000000
1,
1/
#7050000
02
1+
#7100000
0*
