decoder.t.v
// Decoder testbench
`timescale 1 ns / 1 ps
`include "decoder.v"

module testDecoder (); 
    reg addr0, addr1;
    reg enable;
    wire out0,out1,out2,out3;

    // behavioralDecoder decoder (out0,out1,out2,out3,addr0,addr1,enable);
    structuralDecoder decoder (out0,out1,out2,out3,addr0,addr1,enable); // Swap after testing

    initial begin
    $dumpfile("decoder.vcd");
    $dumpvars();
    $display("En A0 A1| O0 O1 O2 O3 | Expected Output");
    enable=0;addr0=0;addr1=0; #500 
    $display("%b  %b  %b |  %b  %b  %b  %b | All false", enable, addr0, addr1, out0, out1, out2, out3);
    enable=0;addr0=1;addr1=0; #500
    $display("%b  %b  %b |  %b  %b  %b  %b | All false", enable, addr0, addr1, out0, out1, out2, out3);
    enable=0;addr0=0;addr1=1; #500 
    $display("%b  %b  %b |  %b  %b  %b  %b | All false", enable, addr0, addr1, out0, out1, out2, out3);
    enable=0;addr0=1;addr1=1; #500 
    $display("%b  %b  %b |  %b  %b  %b  %b | All false", enable, addr0, addr1, out0, out1, out2, out3);
    enable=1;addr0=0;addr1=0; #500 
    $display("%b  %b  %b |  %b  %b  %b  %b | O0 Only", enable, addr0, addr1, out0, out1, out2, out3);
    enable=1;addr0=1;addr1=0; #500 
    $display("%b  %b  %b |  %b  %b  %b  %b | O1 Only", enable, addr0, addr1, out0, out1, out2, out3);
    enable=1;addr0=0;addr1=1; #500 
    $display("%b  %b  %b |  %b  %b  %b  %b | O2 Only", enable, addr0, addr1, out0, out1, out2, out3);
    enable=1;addr0=1;addr1=1; #500 
    $display("%b  %b  %b |  %b  %b  %b  %b | O3 Only", enable, addr0, addr1, out0, out1, out2, out3);
    $dumpflush;
    end

endmodule

decoder.v
// Decoder circuit

// define gates with delays
`define AND and #50
`define NOT not #50

module behavioralDecoder
(
    output out0, out1, out2, out3,
    input address0, address1,
    input enable
);
    // Uses concatenation and shift operators
    assign {out3,out2,out1,out0}=enable<<{address1,address0};
endmodule


module structuralDecoder
(
    output out0, out1, out2, out3,
    input address0, address1,
    input enable
);
    wire address0, address1, enable;
    wire naddress0, naddress1;

    `NOT address0inv(naddress0, address0);
    `NOT address1inv(naddress1, address1);
    `AND andgate0(out0, naddress0, naddress1, enable);
    `AND andgate1(out1, address0, naddress1, enable);
    `AND andgate2(out2, naddress0, address1, enable);
    `AND andgate3(out3, address0, address1, enable);
endmodule

decoder.vcd
$date
	Thu Sep 22 00:51:42 2016
$end
$version
	Icarus Verilog
$end
$timescale
	1ps
$end
$scope module behavioralDecoder $end
$var wire 1 ! address0 $end
$var wire 1 " address1 $end
$var wire 1 # enable $end
$var wire 1 $ out3 $end
$var wire 1 % out2 $end
$var wire 1 & out1 $end
$var wire 1 ' out0 $end
$upscope $end
$scope module testDecoder $end
$var wire 1 ( out3 $end
$var wire 1 ) out2 $end
$var wire 1 * out1 $end
$var wire 1 + out0 $end
$var reg 1 , addr0 $end
$var reg 1 - addr1 $end
$var reg 1 . enable $end
$scope module decoder $end
$var wire 1 , address0 $end
$var wire 1 - address1 $end
$var wire 1 . enable $end
$var wire 1 / naddress0 $end
$var wire 1 0 naddress1 $end
$var wire 1 + out0 $end
$var wire 1 * out1 $end
$var wire 1 ) out2 $end
$var wire 1 ( out3 $end
$upscope $end
$upscope $end
$enddefinitions $end
#0
$dumpvars
x0
x/
0.
0-
0,
x+
x*
x)
x(
x'
x&
x%
x$
z#
z"
z!
$end
#50000
10
1/
0(
0)
0*
0+
#500000
1,
#550000
0/
#1000000
1-
0,
#1050000
00
1/
#1500000
1,
#1550000
0/
#2000000
0-
0,
1.
#2050000
10
1/
#2100000
1+
#2500000
1,
#2550000
0/
1*
#2600000
0+
#3000000
1-
0,
#3050000
00
1/
0*
#3100000
1)
#3500000
1,
#3550000
0/
1(
#3600000
0)
