multiplexer.v
// Multiplexer circuit


// define gates with delays
`define AND and #50
`define OR or #50
`define NOT not #50

module behavioralMultiplexer
(
    output out,
    input address0, address1,
    input in0, in1, in2, in3
);
    // Join single-bit inputs into a bus, use address as index
    wire[3:0] inputs = {in3, in2, in1, in0};
    wire[1:0] address = {address1, address0};
    assign out = inputs[address];
endmodule


module structuralMultiplexer
(
    output out,
    output na0, na1,
    output mid0,mid1,mid2,mid3,
    input address0, address1,
    input in0, in1, in2, in3
);
    wire na0;
    wire na1;
    wire mid0;
    wire mid1;
    wire mid2;
    wire mid3;
    `NOT adinv(na0,address0);
    `NOT adinv(na1,address1);
    `AND andgate(mid0,na0,na1,in0);
    `AND andgate(mid1,na1,address0,in1);
    `AND andgate(mid2,address1,na0,in2);
    `AND andgate(mid3,address0,address1,in3);
    `OR orgate(out,mid0,mid1,mid2,mid3);
endmodule

multiplexer.t.v
// Multiplexer testbench
`timescale 1 ns / 1 ps
`include "multiplexer.v"

module testMultiplexer ();
  	reg address0, address1;
    reg in0,in1,in2,in3;
    wire out;

    //behavioralMultiplexer multiplexer (out,address0,address1,in0,in1,in2,in3);
    structuralMultiplexer multiplexer (out,na0,na1,mid0,mid1,mid2,mid3,address0,address1,in0,in1,in2,in3); // Swap after testing

    initial begin
    $dumpfile("multi.vcd");
    $dumpvars(0,testMultiplexer);
    $display("in0 in1 in2 in3 | a1 a2 | out | Expected Output");

    //All input = 0

    in0=0;in1 =0;in2=0;in3=0;address0=0;address1=0; #1000 

    $display(" %b   %b   %b   %b  | %b   %b |  %b  |  0", in0, in1, in2, in3, address0, address1, out);

    in0=0;in1 =0;in2=0;in3=0;address0=0;address1=1; #1000 

    $display(" %b   %b   %b   %b  | %b   %b |  %b  |  0", in0, in1, in2, in3, address0, address1, out);

    in0=0;in1 =0;in2=0;in3=0;address0=1;address1=0; #1000 

    $display(" %b   %b   %b   %b  | %b   %b |  %b  |  0", in0, in1, in2, in3, address0, address1, out);

    in0=0;in1 =0;in2=0;in3=0;address0=1;address1=1; #1000 

    $display(" %b   %b   %b   %b  | %b   %b |  %b  |  0", in0, in1, in2, in3, address0, address1, out);

    //In3 = 1

    in0=0;in1 =0;in2=0;in3=1;address0=0;address1=0; #1000 

    $display(" %b   %b   %b   %b  | %b   %b |  %b  |  0", in0, in1, in2, in3, address0, address1, out);

    in0=0;in1 =0;in2=0;in3=1;address0=0;address1=1; #1000 

    $display(" %b   %b   %b   %b  | %b   %b |  %b  |  0", in0, in1, in2, in3, address0, address1, out);

    in0=0;in1 =0;in2=0;in3=1;address0=1;address1=0; #1000 

    $display(" %b   %b   %b   %b  | %b   %b |  %b  |  0", in0, in1, in2, in3, address0, address1, out);

    in0=0;in1 =0;in2=0;in3=1;address0=1;address1=1; #1000 

    $display(" %b   %b   %b   %b  | %b   %b |  %b  |  1", in0, in1, in2, in3, address0, address1, out);

    // in2 = 1

    in0=0;in1 =0;in2=1;in3=0;address0=0;address1=0; #1000 

    $display(" %b   %b   %b   %b  | %b   %b |  %b  |  0", in0, in1, in2, in3, address0, address1, out);

    in0=0;in1 =0;in2=1;in3=0;address0=0;address1=1; #1000 

    $display(" %b   %b   %b   %b  | %b   %b |  %b  |  1", in0, in1, in2, in3, address0, address1, out);

    in0=0;in1 =0;in2=1;in3=0;address0=1;address1=0; #1000 

    $display(" %b   %b   %b   %b  | %b   %b |  %b  |  0", in0, in1, in2, in3, address0, address1, out);

    in0=0;in1 =0;in2=1;in3=0;address0=1;address1=1; #1000 

    $display(" %b   %b   %b   %b  | %b   %b |  %b  |  0", in0, in1, in2, in3, address0, address1, out);

    // in1 = 1

    in0=0;in1 =1;in2=0;in3=0;address0=0;address1=0; #1000 

    $display(" %b   %b   %b   %b  | %b   %b |  %b  |  0", in0, in1, in2, in3, address0, address1, out);

    in0=0;in1 =1;in2=0;in3=0;address0=0;address1=1; #1000 

    $display(" %b   %b   %b   %b  | %b   %b |  %b  |  0", in0, in1, in2, in3, address0, address1, out);

    in0=0;in1 =1;in2=0;in3=0;address0=1;address1=0; #1000 

    $display(" %b   %b   %b   %b  | %b   %b |  %b  |  1", in0, in1, in2, in3, address0, address1, out);

    in0=0;in1 =1;in2=0;in3=0;address0=1;address1=1; #1000 

    $display(" %b   %b   %b   %b  | %b   %b |  %b  |  0", in0, in1, in2, in3, address0, address1, out);

    // in0 = 1

    in0=1;in1 =0;in2=0;in3=0;address0=0;address1=0; #1000 

    $display(" %b   %b   %b   %b  | %b   %b |  %b  |  1", in0, in1, in2, in3, address0, address1, out);

    in0=1;in1 =0;in2=0;in3=0;address0=0;address1=1; #1000 

    $display(" %b   %b   %b   %b  | %b   %b |  %b  |  0", in0, in1, in2, in3, address0, address1, out);

    in0=1;in1 =0;in2=0;in3=0;address0=1;address1=0; #1000 

    $display(" %b   %b   %b   %b  | %b   %b |  %b  |  0", in0, in1, in2, in3, address0, address1, out);

    in0=1;in1 =0;in2=0;in3=0;address0=1;address1=1; #1000 

    $display(" %b   %b   %b   %b  | %b   %b |  %b  |  0", in0, in1, in2, in3, address0, address1, out);
    end
endmodule

multi.vcd
$date
	Fri Sep 23 00:03:47 2016
$end
$version
	Icarus Verilog
$end
$timescale
	1ps
$end
$scope module testMultiplexer $end
$var wire 1 ! mid0 $end
$var wire 1 " mid1 $end
$var wire 1 # mid2 $end
$var wire 1 $ mid3 $end
$var wire 1 % na0 $end
$var wire 1 & na1 $end
$var wire 1 ' out $end
$var reg 1 ( address0 $end
$var reg 1 ) address1 $end
$var reg 1 * in0 $end
$var reg 1 + in1 $end
$var reg 1 , in2 $end
$var reg 1 - in3 $end
$scope module multiplexer $end
$var wire 1 . address0 $end
$var wire 1 / address1 $end
$var wire 1 0 in0 $end
$var wire 1 1 in1 $end
$var wire 1 2 in2 $end
$var wire 1 3 in3 $end
$var wire 1 ! mid0 $end
$var wire 1 " mid1 $end
$var wire 1 # mid2 $end
$var wire 1 $ mid3 $end
$var wire 1 % na0 $end
$var wire 1 & na1 $end
$var wire 1 ' out $end
$upscope $end
$upscope $end
$enddefinitions $end
#0
$dumpvars
03
02
01
00
0/
0.
0-
0,
0+
0*
0)
0(
z'
z&
z%
z$
z#
z"
z!
$end
#50000
0$
0#
0"
0!
1%
1&
#100000
0'
#1000000
1)
1/
#1050000
0&
#2000000
0)
0/
1(
1.
#2050000
1&
0%
#3000000
1)
1/
#3050000
0&
#4000000
0)
0/
0(
0.
1-
13
#4050000
1&
1%
#5000000
1)
1/
#5050000
0&
#6000000
0)
0/
1(
1.
#6050000
1&
0%
#7000000
1)
1/
#7050000
0&
1$
#7100000
1'
#8000000
0)
0/
0(
0.
0-
03
1,
12
#8050000
1&
1%
0$
#8100000
0'
#9000000
1)
1/
#9050000
0&
1#
#9100000
1'
#10000000
0)
0/
1(
1.
#10050000
1&
0#
0%
#10100000
0'
#11000000
1)
1/
#11050000
0&
#12000000
0)
0/
0(
0.
0,
02
1+
11
#12050000
1&
1%
#13000000
1)
1/
#13050000
0&
#14000000
0)
0/
1(
1.
#14050000
1&
0%
#14100000
1"
#14150000
1'
#15000000
1)
1/
#15050000
0&
#15100000
0"
#15150000
0'
#16000000
0)
0/
0(
0.
0+
01
1*
10
#16050000
1&
1%
#16100000
1!
#16150000
1'
#17000000
1)
1/
#17050000
0&
#17100000
0!
#17150000
0'
#18000000
0)
0/
1(
1.
#18050000
1&
0%
#19000000
1)
1/
#19050000
0&
