Code/adder.t.v
// Adder testbench
`timescale 1 ns / 1 ps
`include "adder.v"

module testFullAdder();
    reg a, b, carryin;
    wire sum, carryout;

    structuralFullAdder adder (sum, carryout, a, b, carryin);

    initial begin
	$dumpfile("adder.vcd");
	$dumpvars();
	#200
        $display("A B C | Cout Sum | Expected Output");
	a=0; b=0; carryin=0; #1000
	$display("%b %b %b | %b%b | 00", a, b, carryin, carryout, sum);
	a=0; b=0; carryin=1; #1000
	$display("%b %b %b | %b%b | 01", a, b, carryin, carryout, sum);
	a=0; b=1; carryin=0; #1000
	$display("%b %b %b | %b%b | 01", a, b, carryin, carryout, sum);
	a=0; b=1; carryin=1; #1000
	$display("%b %b %b | %b%b | 10", a, b, carryin, carryout, sum);
	a=1; b=0; carryin=0; #1000
	$display("%b %b %b | %b%b | 01", a, b, carryin, carryout, sum);
	a=1; b=0; carryin=1; #1000
	$display("%b %b %b | %b%b | 10", a, b, carryin, carryout, sum);
	a=1; b=1; carryin=0; #1000
	$display("%b %b %b | %b%b | 10", a, b, carryin, carryout, sum);
	a=1; b=1; carryin=1; #1000
	$display("%b %b %b | %b%b | 11", a, b, carryin, carryout, sum);
    end
endmodule

Code/adder.v
`define And and #50
`define Or or #50
`define Not not #50

// Adder circuit

module behavioralFullAdder
(
    output sum, 
    output carryout,
    input a, 
    input b, 
    input carryin
);
    // Uses concatenation operator and built-in '+'
    assign {carryout, sum}=a+b+carryin;
endmodule

module structuralFullAdder
(
    output sum, 
    output carryout,
    input a, 
    input b, 
    input carryin
);
wire s1, c1, c2;

xor(s1, a, b);
xor(sum, s1, carryin);

and(c1, s1, carryin);
and(c2, a, b);
or(carryout, c1, c2);
    
endmodule

Code/adder.vcd
$date
	Mon Sep 19 18:58:14 2016
$end
$version
	Icarus Verilog
$end
$timescale
	1ps
$end
$scope module behavioralFullAdder $end
$var wire 1 ! a $end
$var wire 1 " b $end
$var wire 1 # carryin $end
$var wire 1 $ carryout $end
$var wire 1 % sum $end
$upscope $end
$scope module testFullAdder $end
$var wire 1 & carryout $end
$var wire 1 ' sum $end
$var reg 1 ( a $end
$var reg 1 ) b $end
$var reg 1 * carryin $end
$scope module adder $end
$var wire 1 + a $end
$var wire 1 , b $end
$var wire 1 - c1 $end
$var wire 1 . c2 $end
$var wire 1 / carryin $end
$var wire 1 & carryout $end
$var wire 1 0 s1 $end
$var wire 1 ' sum $end
$upscope $end
$upscope $end
$enddefinitions $end
#0
$dumpvars
x0
x/
x.
x-
x,
x+
x*
x)
x(
x'
x&
x%
x$
z#
z"
z!
$end
#200000
0&
0'
0-
00
0.
0*
0/
0)
0,
0(
0+
#1200000
1'
1*
1/
#2200000
10
0*
0/
1)
1,
#3200000
1&
0'
1-
1*
1/
#4200000
0&
1'
0-
0*
0/
0)
0,
1(
1+
#5200000
1&
0'
1-
1*
1/
#6200000
0-
00
1.
0*
0/
1)
1,
#7200000
1'
1*
1/
