Code/decoder.t.v
// Decoder testbench
`timescale 1 ns / 1 ps
`include "decoder.v"

module testDecoder (); 
    reg addr0, addr1;
    reg enable;
    wire out0,out1,out2,out3;

    //behavioralDecoder decoder (out0,out1,out2,out3,addr0,addr1,enable);
    structuralDecoder decoder (out0,out1,out2,out3,addr0,addr1,enable); // Swap after testing

    initial begin
    $dumpfile("decoder.vcd");
    $dumpvars();
    #200
    $display("En A0 A1| O0 O1 O2 O3 | Expected Output");
    enable=0;addr0=0;addr1=0; #1000 
    $display("%b  %b  %b |  %b  %b  %b  %b | All false", enable, addr0, addr1, out0, out1, out2, out3);
    enable=0;addr0=1;addr1=0; #1000
    $display("%b  %b  %b |  %b  %b  %b  %b | All false", enable, addr0, addr1, out0, out1, out2, out3);
    enable=0;addr0=0;addr1=1; #1000 
    $display("%b  %b  %b |  %b  %b  %b  %b | All false", enable, addr0, addr1, out0, out1, out2, out3);
    enable=0;addr0=1;addr1=1; #1000 
    $display("%b  %b  %b |  %b  %b  %b  %b | All false", enable, addr0, addr1, out0, out1, out2, out3);
    enable=1;addr0=0;addr1=0; #1000 
    $display("%b  %b  %b |  %b  %b  %b  %b | O0 Only", enable, addr0, addr1, out0, out1, out2, out3);
    enable=1;addr0=1;addr1=0; #1000 
    $display("%b  %b  %b |  %b  %b  %b  %b | O1 Only", enable, addr0, addr1, out0, out1, out2, out3);
    enable=1;addr0=0;addr1=1; #1000 
    $display("%b  %b  %b |  %b  %b  %b  %b | O2 Only", enable, addr0, addr1, out0, out1, out2, out3);
    enable=1;addr0=1;addr1=1; #1000 
    $display("%b  %b  %b |  %b  %b  %b  %b | O3 Only", enable, addr0, addr1, out0, out1, out2, out3);
    end

endmodule

Code/decoder.v
// Decoder circuit

module behavioralDecoder
(
    output out0, out1, out2, out3,
    input address0, address1,
    input enable
);
    // Uses concatenation and shift operators
    assign {out3,out2,out1,out0}=enable<<{address1,address0};
endmodule


module structuralDecoder
(
    output out0, out1, out2, out3,
    input address0, address1,
    input enable
);
    wire nadd0, nadd1, d0, d1, d2, d3;
    not(nadd0, address0);
    not(nadd1, address1);
    and(d0, nadd0, nadd1);
    and(d1, address0, nadd1);
    and(d2, nadd0, address1);
    and(d3, address0, address1);
    and(out0, d0, enable);
    and(out1, d1, enable);
    and(out2, d2, enable);
    and(out3, d3, enable);
endmodule

Code/decoder.vcd
$date
	Mon Sep 19 19:04:01 2016
$end
$version
	Icarus Verilog
$end
$timescale
	1ps
$end
$scope module behavioralDecoder $end
$var wire 1 ! address0 $end
$var wire 1 " address1 $end
$var wire 1 # enable $end
$var wire 1 $ out0 $end
$var wire 1 % out1 $end
$var wire 1 & out2 $end
$var wire 1 ' out3 $end
$upscope $end
$scope module testDecoder $end
$var wire 1 ( out0 $end
$var wire 1 ) out1 $end
$var wire 1 * out2 $end
$var wire 1 + out3 $end
$var reg 1 , addr0 $end
$var reg 1 - addr1 $end
$var reg 1 . enable $end
$scope module decoder $end
$var wire 1 / address0 $end
$var wire 1 0 address1 $end
$var wire 1 1 d0 $end
$var wire 1 2 d1 $end
$var wire 1 3 d2 $end
$var wire 1 4 d3 $end
$var wire 1 5 enable $end
$var wire 1 6 nadd0 $end
$var wire 1 7 nadd1 $end
$var wire 1 ( out0 $end
$var wire 1 ) out1 $end
$var wire 1 * out2 $end
$var wire 1 + out3 $end
$upscope $end
$upscope $end
$enddefinitions $end
#0
$dumpvars
x7
x6
x5
x4
x3
x2
x1
x0
x/
x.
x-
x,
x+
x*
x)
x(
x'
x&
x%
x$
z#
z"
z!
$end
#200000
11
17
03
16
02
04
0(
0)
0*
0+
0-
00
0,
0/
0.
05
#1200000
01
06
12
1,
1/
#2200000
07
13
16
02
1-
10
0,
0/
#3200000
03
06
14
1,
1/
#4200000
1(
11
17
16
04
0+
0-
00
0,
0/
1.
15
#5200000
0(
01
1)
06
12
1,
1/
#6200000
1*
0)
07
13
16
02
1-
10
0,
0/
#7200000
0*
03
1+
06
14
1,
1/
