multiplexer.v
// Multiplexer circuit
`define AND and #50
`define OR or #50
`define NOT not #50

module behavioralMultiplexer
(
    output out,
    input address0, address1,
    input in0, in1, in2, in3
);
    // Join single-bit inputs into a bus, use address as index
    wire[3:0] inputs = {in3, in2, in1, in0};
    wire[1:0] address = {address1, address0};
    assign out = inputs[address];
endmodule


module structuralMultiplexer
(
    output out,
    input address0, address1,
    input in0, in1, in2, in3
);
    wire [1:0] nA;
    wire [0:3] andAddress, andOut;
    `NOT ng0(nA[0], address0);
    `NOT ng1(nA[1], address1);
    `AND ag0(andAddress[0], nA[0], nA[1]);
    `AND ag1(andAddress[1], address0, nA[1]);
    `AND ag2(andAddress[2], nA[0], address1);
    `AND ag3(andAddress[3], address0, address1);
    `AND ag4(andOut[0], andAddress[0], in0);
    `AND ag5(andOut[1], andAddress[1], in1);
    `AND ag6(andOut[2], andAddress[2], in2);
    `AND ag7(andOut[3], andAddress[3], in3);
    `OR og(out, andOut[0], andOut[1], andOut[2], andOut[3]);

endmodule

multiplexer.t.v
// Multiplexer testbench
`timescale 1 ns / 1 ps
`include "multiplexer.v"

module testMultiplexer ();
	reg address0, address1, in0, in1, in2, in3;
	wire out;
	structuralMultiplexer multiplexer (out, address0, address1, in0, in1, in2, in3);

	initial begin
	    $dumpfile("multiplexer.vcd");
		$dumpvars(0, testMultiplexer);

	    $display("address0 | address1 | in0 | in1 | in2 | in3 | out | Expected Out |");            // Prints header for truth table
	    address0=0;address1=0;in0=0; #1000                               // Set A and B, wait for update (#1)
	    $display("    %b    |    %b     |  %b  |  %b  |  %b  |  %b  |  %b  |      0      |", address0, address1, in0, in1, in2, in3, out);
	    address0=0;address1=0;in0=1; #1000                                 // Set A and B, wait for update (#1)
	    $display("    %b    |    %b     |  %b  |  %b  |  %b  |  %b  |  %b  |      1      |", address0, address1, in0, in1, in2, in3, out);
	    address0=0;address1=1;in2=0; #1000                                // Set A and B, wait for update (#1)
	    $display("    %b    |    %b     |  %b  |  %b  |  %b  |  %b  |  %b  |      0      |", address0, address1, in0, in1, in2, in3, out);
	    address0=0;address1=1;in2=1; #1000                                 // Set A and B, wait for update (#1)
	    $display("    %b    |    %b     |  %b  |  %b  |  %b  |  %b  |  %b  |      1      |", address0, address1, in0, in1, in2, in3, out);
		address0=1;address1=0;in1=0; #1000                                // Set A and B, wait for update (#1)
	    $display("    %b    |    %b     |  %b  |  %b  |  %b  |  %b  |  %b  |      0      |", address0, address1, in0, in1, in2, in3, out);
	    address0=1;address1=0;in1=1; #1000                                // Set A and B, wait for update (#1)
	    $display("    %b    |    %b     |  %b  |  %b  |  %b  |  %b  |  %b  |      1      |", address0, address1, in0, in1, in2, in3, out);
	    address0=1;address1=1;in3=0; #1000                                 // Set A and B, wait for update (#1)
	    $display("    %b    |    %b     |  %b  |  %b  |  %b  |  %b  |  %b  |      0      |", address0, address1, in0, in1, in2, in3, out);
	    address0=1;address1=1;in3=1; #1000                                 // Set A and B, wait for update (#1)
	    $display("    %b    |    %b     |  %b  |  %b  |  %b  |  %b  |  %b  |      1      |", address0, address1, in0, in1, in2, in3, out);
	   
	end
endmodule

picsAndWaveforms/multiplexer.vcd
$date
	Fri Sep 23 22:20:41 2016
$end
$version
	Icarus Verilog
$end
$timescale
	1ps
$end
$scope module testMultiplexer $end
$var wire 1 ! out $end
$var reg 1 " address0 $end
$var reg 1 # address1 $end
$var reg 1 $ in0 $end
$var reg 1 % in1 $end
$var reg 1 & in2 $end
$var reg 1 ' in3 $end
$scope module multiplexer $end
$var wire 1 " address0 $end
$var wire 1 # address1 $end
$var wire 1 $ in0 $end
$var wire 1 % in1 $end
$var wire 1 & in2 $end
$var wire 1 ' in3 $end
$var wire 1 ! out $end
$var wire 2 ( nA [1:0] $end
$var wire 4 ) andOut [0:3] $end
$var wire 4 * andAddress [0:3] $end
$upscope $end
$upscope $end
$enddefinitions $end
#0
$dumpvars
bx *
bx )
bx (
x'
x&
x%
0$
0#
0"
x!
$end
#50000
b11 (
b0xxx )
bx000 *
#100000
b1000 *
b0 )
#150000
0!
#1000000
1$
#1050000
b1000 )
#1100000
1!
#2000000
0&
1#
#2050000
b1 (
b1010 *
#2100000
b10 *
#2150000
b0 )
#2200000
0!
#3000000
1&
#3050000
b10 )
#3100000
1!
#4000000
0%
0#
1"
#4050000
b0 *
b10 (
#4100000
b100 *
b0 )
#4150000
0!
#5000000
1%
#5050000
b100 )
#5100000
1!
#6000000
0'
1#
#6050000
b0 (
b101 *
#6100000
b1 *
#6150000
b0 )
#6200000
0!
#7000000
1'
#7050000
b1 )
#7100000
1!
